CapBypassWrapped/__init__.py
CapBypassWrapped/main.py
capbypasswrapped-2.4.0.dist-info/METADATA
capbypasswrapped-2.4.0.dist-info/WHEEL
capbypasswrapped-2.4.0.dist-info/top_level.txt
capbypasswrapped-2.4.0.dist-info/RECORD
