Metadata-Version: 2.1
Name: capbypasswrapped
Version: 2.4.0
Requires-Dist: httpx
